pyscf/dispersion/dftd4.py
pyscf/dispersion/gcp.py
pyscf/dispersion/__init__.py
pyscf/dispersion/dftd3.py
pyscf/dispersion/tests/test_d3.py
pyscf/dispersion/tests/test_gcp.py
pyscf/dispersion/tests/test_d4.py
pyscf/lib/libdftd4.so
pyscf/lib/libs-dftd3.so
pyscf_dispersion-1.4.1.dist-info/WHEEL
pyscf_dispersion-1.4.1.dist-info/METADATA
pyscf_dispersion-1.4.1.dist-info/top_level.txt
pyscf_dispersion-1.4.1.dist-info/RECORD
pyscf_dispersion-1.4.1.dist-info/licenses/LICENSE
pyscf_dispersion.libs/libopenblas-r0-f650aae0.3.3.so
pyscf_dispersion.libs/libgfortran-040039e1.so.5.0.0
pyscf_dispersion.libs/libquadmath-96973f99.so.0.0.0
pyscf_dispersion.libs/libgfortran-91cc3cb1.so.3.0.0
