Metadata-Version: 2.4
Name: pyscf-dispersion
Version: 1.4.1
Summary: DFTD3 and DFTD4 interfaces
Author-email: Qiming Sun <osirpt.sun@gmail.com>
Maintainer-email: Qiming Sun <osirpt.sun@gmail.com>
License: Apache-2.0
Project-URL: Homepage, http://www.pyscf.org
Project-URL: Repository, https://github.com/pyscf/dftd3-builder
Project-URL: Documentation, http://www.pyscf.org
Classifier: Development Status :: 4 - Beta
Classifier: Intended Audience :: Science/Research
Classifier: Intended Audience :: Developers
Classifier: License :: OSI Approved :: Apache Software License
Classifier: Programming Language :: C
Classifier: Programming Language :: Python
Classifier: Programming Language :: Python :: 3.8
Classifier: Programming Language :: Python :: 3.9
Classifier: Programming Language :: Python :: 3.10
Classifier: Programming Language :: Python :: 3.11
Classifier: Programming Language :: Python :: 3.12
Classifier: Topic :: Software Development
Classifier: Topic :: Scientific/Engineering
Classifier: Operating System :: POSIX
Classifier: Operating System :: Unix
Classifier: Operating System :: MacOS
License-File: LICENSE
Requires-Dist: pyscf
Dynamic: license-file
